{
  "parent": "minecraft:recipes/root",
  "rewards": {
    "recipes": [
      "lostworlds:raised_pavement"
    ]
  },
  "criteria": {
    "has_pavement": {
      "trigger": "minecraft:inventory_changed",
      "conditions": {
        "items": [
          {
            "items": [
              "lostworlds:pavement"
            ]
          }
        ]
      }
    },
    "has_the_recipe": {
      "trigger": "minecraft:recipe_unlocked",
      "conditions": {
        "recipe": "lostworlds:raised_pavement"
      }
    }
  },
  "requirements": [
    [
      "has_pavement",
      "has_the_recipe"
    ]
  ]
}