{
	"format_version": "1.12.0",
	"minecraft:geometry": [
		{
			"description": {
				"identifier": "geometry.great_auk",
				"texture_width": 64,
				"texture_height": 64,
				"visible_bounds_width": 3,
				"visible_bounds_height": 2.5,
				"visible_bounds_offset": [
					0,
					0.75,
					0
				]
			},
			"bones": [
				{
					"name": "Great_Auk",
					"pivot": [
						0,
						8,
						1
					]
				},
				{
					"name": "body",
					"parent": "Great_Auk",
					"pivot": [
						0,
						8,
						1
					]
				},
				{
					"name": "neck",
					"parent": "body",
					"pivot": [
						0,
						10,
						0
					]
				},
				{
					"name": "head",
					"parent": "neck",
					"pivot": [
						0,
						12,
						-1
					]
				},
				{
					"name": "wing1",
					"parent": "body",
					"pivot": [
						2,
						9,
						0
					]
				},
				{
					"name": "wing2",
					"parent": "body",
					"pivot": [
						-2,
						9,
						0
					],
					"cubes": [
						{
							"origin": [
								-1,
								-3,
								-1
							],
							"size": [
								1,
								6,
								3
							],
							"pivot": [
								0,
								0,
								0
							],
							"rotation": [
								0,
								0,
								90
							],
							"uv": [
								20,
								0
							]
						}
					]
				},
				{
					"name": "tail",
					"parent": "body",
					"pivot": [
						0,
						2.5,
						3.25
					]
				},
				{
					"name": "leg1",
					"parent": "Great_Auk",
					"pivot": [
						1,
						2,
						1.75
					]
				},
				{
					"name": "leg2",
					"parent": "Great_Auk",
					"pivot": [
						-1,
						2,
						1.75
					]
				}
			]
		}
	]
}
