{
	"format_version": "1.12.0",
	"minecraft:geometry": [
		{
			"description": {
				"identifier": "geometry.utahraptor",
				"texture_width": 128,
				"texture_height": 128,
				"visible_bounds_width": 9,
				"visible_bounds_height": 3.5,
				"visible_bounds_offset": [
					0,
					1.25,
					0
				]
			},
			"bones": [
				{
					"name": "Utahraptor",
					"pivot": [
						0,
						21,
						-8
					]
				},
				{
					"name": "body",
					"parent": "Utahraptor",
					"pivot": [
						10,
						-3,
						6
					],
					"rotation": [
						0,
						0,
						90
					]
				},
				{
					"name": "rightwing",
					"parent": "body",
					"pivot": [
						5,
						-8,
						1
					],
					"cubes": [
						{
							"origin": [
								3,
								-19,
								-3
							],
							"size": [
								4,
								13,
								7
							],
							"uv": [
								0,
								84
							],
							"mirror": true
						},
						{
							"origin": [
								5,
								-21,
								-3
							],
							"size": [
								0,
								2,
								4
							],
							"uv": [
								0,
								0
							]
						}
					]
				}
			]
		}
	]
}
